discord_buttons_plugin/__init__.py
discord_buttons_plugin/__main__.py
discord_buttons_plugin/models.py
discord_buttons_plugin/types.py
discord_buttons_plugin-0.1.2.dist-info/METADATA
discord_buttons_plugin-0.1.2.dist-info/WHEEL
discord_buttons_plugin-0.1.2.dist-info/top_level.txt
discord_buttons_plugin-0.1.2.dist-info/RECORD
