Metadata-Version: 2.1
Name: discord_buttons_plugin
Version: 0.1.2
Summary: A simple module to use for buttons in discord.py
Home-page: https://github.com/SilentJungle399/discord_buttons_plugin
Author: SilentJungle399
License: UNKNOWN
Platform: UNKNOWN
Classifier: Programming Language :: Python :: 3
Classifier: License :: OSI Approved :: MIT License
Classifier: Operating System :: OS Independent
Requires-Python: >=3.6
